call_detector/__init__.py
call_detector/__main__.py
call_detector/camera.py
call_detector/microphone.py
call_detector/publishers.py
call_detector-0.2.4.dist-info/METADATA
call_detector-0.2.4.dist-info/WHEEL
call_detector-0.2.4.dist-info/entry_points.txt
call_detector-0.2.4.dist-info/top_level.txt
call_detector-0.2.4.dist-info/zip-safe
call_detector-0.2.4.dist-info/RECORD
