Metadata-Version: 2.1
Name: call-detector
Version: 0.2.4
Summary: Detects if the user is an online call, publishes gathered information to an MQTT broker
Home-page: https://github.com/zhulik/call_detector
Author: Gleb Sinyavskiy
Author-email: zhulik.gleb@gmail.com
License: The MIT License
Keywords: home-automation,home-assistant,mqtt,pulseaudio,pipewire,camera
Platform: UNKNOWN
Classifier: Development Status :: 3 - Alpha
Classifier: Intended Audience :: End Users/Desktop
Classifier: Natural Language :: English
Classifier: License :: OSI Approved :: MIT License
Classifier: Programming Language :: Python :: 3.9
Classifier: Topic :: Home Automation
Requires-Dist: pulsectl-asyncio (>=0.1.5)
Requires-Dist: gmqtt (>=0.6.9)
Requires-Dist: minotaur (>=0.0.4)
Requires-Dist: click (>=8.0.0)
Requires-Dist: async-timeout (>=3.0.1)
